{
    "instance_observation_query" : {"queryType":"groupBy","dataSource":"ml_observation","granularity":"all","dimensions":["questionName","questionAnswer","school","districtName","schoolName","remarks","entityType","observationName","observationId","questionResponseType","questionResponseLabel","questionId","questionExternalId","instanceId","instanceParentQuestion","instanceParentResponsetype","instanceParentId","questionSequenceByEcm","instanceParentExternalId","instanceParentEcmSequence"],"filter":{"type":"and","fields":[{"type":"selector","dimension":"observationSubmissionId","value":""}]},"aggregations":[],"postAggregations":[],"limitSpec":{},"intervals":["1901-01-01T00:00:00+00:00/2101-01-01T00:00:00+00:00"]},

    "instance_observation_score_query" : {"queryType":"groupBy","dataSource":"ml_observation_qa","dimensions":["questionName","questionAnswer","questionExternalId","questionResponseType","minScore","maxScore","totalScore","scoreAchieved","observationName"],"aggregations":[{"type":"count","name":"count"}],"granularity":"all","postAggregations":[],"intervals":"1901-01-01T00:00:00+00:00/2101-01-01T00:00:00+00:00","filter":{"type":"and","fields":[{"type":"selector","dimension":"observationSubmissionId","value":""},{"type":"or","fields":[{"type":"selector","dimension":"questionResponseType","value":"radio"},{"type":"selector","dimension":"questionResponseType","value":"multiselect"},{"type":"selector","dimension":"questionResponseType","value":"slider"}]}]},"limitSpec":{"type":"default","limit":10000,"columns":[{"dimension":"count","direction":"descending"}]}},

    "entity_observation_query" : {"queryType":"groupBy","dataSource":"ml_observation_dev","granularity":"all","dimensions":["completedDate","questionName","questionAnswer","school","schoolName","entityType","observationName","observationId","questionResponseType","questionResponseLabel","observationSubmissionId","questionId","questionExternalId","instanceId","instanceParentQuestion","instanceParentResponsetype","instanceParentId","instanceParentEcmSequence","instanceParentExternalId"],"filter":{"type":"and","fields":[{"type":"selector","dimension":"school","value":""},{"type":"selector","dimension":"observationId","value":""}]},"aggregations":[],"postAggregations":[],"intervals":["1901-01-01T00:00:00+00:00/2101-01-01T00:00:00+00:00"]},

    "entity_observation_report_query" : {"queryType":"groupBy","dataSource":"ml_observations_dev","granularity":"all","dimensions":["questionName","questionAnswer","observationName","observationId","districtName","questionResponseType","questionResponseLabel","observationSubmissionId","questionId","questionExternalId","instanceId","instanceParentQuestion","instanceParentResponsetype","instanceParentId"],"filter":{"type":"and","fields":[{"type":"selector","dimension":"","value":""},{"type":"selector","dimension":"observationId","value":""}]},"aggregations":[],"postAggregations":[],"intervals":["1901-01-01T00:00:00+00:00/2101-01-01T00:00:00+00:00"]},

    "entity_observation_score_query" : {"queryType":"groupBy","dataSource":"ml_observation_qa","dimensions":["questionName","questionExternalId","questionResponseType","minScore","maxScore","observationSubmissionId","school","schoolName","districtName","questionId","completedDate","observationName"],"aggregations":[{"type":"count","name":"count"}],"granularity":"all","postAggregations":[],"intervals":"1901-01-01T00:00:00+00:00/2101-01-01T00:00:00+00:00","filter":{"type":"and","fields":[{"type":"or","fields":[{"type":"selector","dimension":"questionResponseType","value":"radio"},{"type":"selector","dimension":"questionResponseType","value":"multiselect"},{"type":"selector","dimension":"questionResponseType","value":"slider"}]},{"type":"and","fields":[{"type":"selector","dimension":"school","value":"" },{"type":"selector","dimension":"observationId","value":""}]}]},"limitSpec":{"type":"default","limit":10000,"columns":[{"dimension":"count","direction":"descending"}]}},

    "observation_report_query" : {"queryType":"groupBy","dataSource":"ml_observation","granularity":"all","dimensions":["questionName","questionAnswer","entityType","observationName","observationId","questionResponseType","questionResponseLabel","observationSubmissionId","questionId","questionExternalId","instanceId","instanceParentQuestion","instanceParentResponsetype","instanceParentId","instanceParentEcmSequence","instanceParentExternalId"],"filter":{"type":"and","fields":[{"type":"selector","dimension":"observationId","value":""}]},"aggregations":[],"postAggregations":[],"intervals":["1901-01-01T00:00:00+00:00/2101-01-01T00:00:00+00:00"]},
    
    "observation_score_report_query" : {"queryType":"groupBy","dataSource":"ml_observation_qa","dimensions":["observationSubmissionId","completedDate","scoreAchieved","observationName","minScore","maxScore","questionName","questionExternalId","questionResponseType"],"aggregations":[{"type":"count","name":"count"}],"granularity":"all","postAggregations":[],"intervals":"1901-01-01T00:00:00+00:00/2101-01-01T00:00:00+00:00","filter":{"type":"and","fields":[{"type":"selector","dimension":"observationId","value":""},{"type":"or","fields":[{"type":"selector","dimension":"questionResponseType","value":"multiselect"},{"type":"selector","dimension":"questionResponseType","value":"radio"},{"type":"selector","dimension":"questionResponseType","value":"slider"}]}]},"limitSpec":{"type":"default","limit":10000,"columns":[{"dimension":"count","direction":"descending"}]}},

    "list_observation_names_query" : {"queryType":"groupBy","dataSource":"ml_observation","granularity":"all","dimensions":["observationId","observationName"],"filter":{"type":"and","fields":[{"type":"selector","dimension":"","value":""},{"type":"or","fields":[{"type":"and","fields":[{"type":"selector","dimension":"userId","value":""},{"type":"selector","dimension":"isAPrivateProgram","value":true}]},{"type":"selector","dimension":"isAPrivateProgram","value":false}]}]},"aggregations":[],"postAggregations":[],"intervals":["1901-01-01T00:00:00+00:00/2101-01-01T00:00:00+00:00"]},

    "solutions_list_query" : {"queryType":"groupBy","dataSource":"ml_observation","granularity":"all","dimensions":["solutionId","solutionName","totalScore"],"filter":{"type":"and","fields":[{"type":"selector","dimension":"","value":""},{"type":"or","fields":[{"type":"and","fields":[{"type":"selector","dimension":"createdBy","value":""},{"type":"selector","dimension":"isAPrivateProgram","value":true}]},{"type":"selector","dimension":"isAPrivateProgram","value":false}]}]},"aggregations":[],"postAggregations":[],"intervals":["1901-01-01T00:00:00+00:00/2101-01-01T00:00:00+00:00"]},

    "entity_solution_report_query" : {"queryType":"groupBy","dataSource":"ml_observations_dev","granularity":"all","dimensions":["solutionId","solutionName","questionName","questionAnswer","observationName","observationId","questionResponseType","questionResponseLabel","observationSubmissionId","questionId","questionExternalId","instanceId","instanceParentQuestion","instanceParentResponsetype","instanceParentId"],"filter":{"type":"and","fields":[{"type":"selector","dimension":"","value":""},{"type":"selector","dimension":"solutionId","value":""}]},"aggregations":[],"postAggregations":[],"intervals":["1901-01-01T00:00:00+00:00/2101-01-01T00:00:00+00:00"]},

    "instance_criteria_report_query" : {"queryType":"groupBy","dataSource":"ml_observation","granularity":"all","dimensions":["questionName","questionAnswer","school","districtName","schoolName","remarks","entityType","observationName","observationId","questionResponseType","questionResponseLabel","questionId","questionExternalId","instanceId","instanceParentQuestion","instanceParentResponsetype","instanceParentId","questionSequenceByEcm","instanceParentExternalId","instanceParentEcmSequence","criteriaName","criteriaId","instanceParentCriteriaName","instanceParentCriteriaId"],"filter":{"type":"selector","dimension":"observationSubmissionId","value":""},"aggregations":[],"postAggregations":[],"limitSpec":{"type":"default","columns":[{"dimension":"questionExternalId","direction":"ascending"}]},"intervals":["1901-01-01T00:00:00+00:00/2101-01-01T00:00:00+00:00"]},

    "instance_score_criteria_report_query" : {"queryType":"groupBy","dataSource":"ml_observation","dimensions":["questionName","schoolName","districtName","questionAnswer","questionExternalId","questionResponseType","minScore","maxScore","totalScore","scoreAchieved","observationName","criteriaName","criteriaId"],"aggregations":[{"type":"count","name":"count"}],"granularity":"all","postAggregations":[],"intervals":"1901-01-01T00:00:00+00:00/2101-01-01T00:00:00+00:00","filter":{"type":"and","fields":[{"type":"selector","dimension":"observationSubmissionId","value":""},{"type":"or","fields":[{"type":"selector","dimension":"questionResponseType","value":"radio"},{"type":"selector","dimension":"questionResponseType","value":"multiselect"},{"type":"selector","dimension":"questionResponseType","value":"slider"}]}]},"limitSpec":{"type":"default","columns":[{"dimension":"count","direction":"descending"}]}},

    "entity_criteria_report_query" : {"queryType":"groupBy","dataSource":"ml_observation","granularity":"all","dimensions":["completedDate","questionName","questionAnswer","school","schoolName","entityType","observationName","observationId","questionResponseType","questionResponseLabel","observationSubmissionId","questionId","questionExternalId","instanceId","instanceParentQuestion","instanceParentResponsetype","instanceParentId","instanceParentEcmSequence","instanceParentExternalId","criteriaName","criteriaId","instanceParentCriteriaName","instanceParentCriteriaId"],"filter":{"type":"and","fields":[{"type":"selector","dimension":"school","value":""},{"type":"selector","dimension":"observationId","value":""}]},"aggregations":[],"postAggregations":[],"intervals":["1901-01-01T00:00:00+00:00/2101-01-01T00:00:00+00:00"]},

    "entity_score_criteria_report_query" : {"queryType":"groupBy","dataSource":"ml_observation","dimensions":["questionName","questionExternalId","questionResponseType","minScore","maxScore","observationSubmissionId","school","schoolName","districtName","questionId","completedDate","observationName","criteriaName","criteriaId"],"aggregations":[{"type":"count","name":"count"}],"granularity":"all","postAggregations":[],"intervals":"1901-01-01T00:00:00+00:00/2101-01-01T00:00:00+00:00","filter":{"type":"and","fields":[{"type":"or","fields":[{"type":"selector","dimension":"questionResponseType","value":"radio"},{"type":"selector","dimension":"questionResponseType","value":"multiselect"},{"type":"selector","dimension":"questionResponseType","value":"slider"}]},{"type":"and","fields":[{"type":"selector","dimension":"school","value":"" },{"type":"selector","dimension":"observationId","value":""}]}]},"limitSpec":{"type":"default","columns":[{"dimension":"count","direction":"descending"}]}},

    "observation_criteria_report_query" : {"queryType":"groupBy","dataSource":"ml_observation","granularity":"all","dimensions":["questionName","questionAnswer","entityType","observationName","observationId","questionResponseType","questionResponseLabel","observationSubmissionId","questionId","questionExternalId","instanceId","instanceParentQuestion","instanceParentResponsetype","instanceParentId","instanceParentEcmSequence","instanceParentExternalId","criteriaName","criteriaId","instanceParentCriteriaName","instanceParentCriteriaId"],"filter":{"type":"selector","dimension":"observationId","value":""},"aggregations":[],"postAggregations":[],"intervals":["1901-01-01T00:00:00+00:00/2101-01-01T00:00:00+00:00"]},

    "observation_score_criteria_report_query" : {"queryType":"groupBy","dataSource":"ml_observation","dimensions":["school","schoolName","observationSubmissionId","completedDate","scoreAchieved","observationName","minScore","maxScore","questionName","questionExternalId","questionResponseType","criteriaName","criteriaId"],"aggregations":[{"type":"count","name":"count"}],"granularity":"all","postAggregations":[],"intervals":"1901-01-01T00:00:00+00:00/2101-01-01T00:00:00+00:00","filter":{"type":"and","fields":[{"type":"selector","dimension":"observationId","value":""},{"type":"or","fields":[{"type":"selector","dimension":"questionResponseType","value":"multiselect"},{"type":"selector","dimension":"questionResponseType","value":"radio"},{"type":"selector","dimension":"questionResponseType","value":"slider"}]}]},"limitSpec":{"type":"default","columns":[{"dimension":"count","direction":"descending"}]}},

    "list_all_evidence_query" : {"queryType":"groupBy","dataSource":"ml_observation","granularity":"all","dimensions":["questionName","questionId","questionExternalId","remarks","fileName","fileSourcePath"],"filter":{},"aggregations":[],"postAggregations":[],"limitSpec":{"type":"default","limit":10000,"columns":[{"dimension":"questionExternalId","direction":"ascending"}]},"intervals":["1901-01-01T00:00:00+00:00/2101-01-01T00:00:00+00:00"]},

    "get_evidence_query" : {"queryType":"groupBy","dataSource":"ml_observation_evidence_dev","granularity":"all","dimensions":["fileSourcePath","questionExternalId","observationSubmissionId","entity","observationId","evidence_count","total_evidences","fileName"],"filter":{},"aggregations":[],"postAggregations":[],"intervals":["1901-01-01T00:00:00+00:00/2101-01-01T00:00:00+00:00"]},

    "entity_level_assessment_report_query" : {"queryType":"groupBy","dataSource":"ml_assessments","granularity":"all","dimensions":["submissionId","completedDate","domainName","criteriaDescription","level","label","programName","solutionName","childExternalid","childName","childType"],"filter":{"type":"and","fields":[{"type":"selector","dimension":"","value":""},{"type":"selector","dimension":"programId","value":""},{"type":"selector","dimension":"solutionId","value":""},{"type":"selector","dimension":"childType","value":"criteria"}]},"aggregations":[{"fieldName":"domainName","fieldNames":["domainName"],"type":"count","name":"domainNameCount"}],"postAggregations":[],"intervals":["1901-01-01T00:00:00+00:00/2101-01-01T00:00:00+00:00"]},

    "list_improvement_projects_query" : {"queryType":"groupBy","dataSource":"ml_assessment_dev","granularity":"all","dimensions":["criteriaDescription","level","label","imp_project_title","imp_project_id","imp_project_goal","imp_project_externalId"],"filter":{"type":"and","fields":[]},"aggregations":[],"postAggregations":[],"intervals":["1901-01-01T00:00:00+00:00/2101-01-01T00:00:00+00:00"]},

    "list_entities_query" : {"queryType":"groupBy","dataSource":"ml_assessment","granularity":"all","dimensions":["solutionName","solutionId","solutionDescription","solutionExternalId"],"filter":{},"aggregations":[],"postAggregations":[],"intervals":["1901-01-01T00:00:00+00:00/2101-01-01T00:00:00+00:00"]},

    "list_assessment_programs_query" : {"queryType":"groupBy","dataSource":"ml_assessment","granularity":"all","dimensions":["programName","programId","programDescription","programExternalId","solutionName","solutionId","solutionDescription","solutionExternalId"],"filter":{"type":"and","fields":[{"type":"selector","dimension":"","value":""},{"type":"or","fields":[{"type":"and","fields":[{"type":"selector","dimension":"userId","value":""},{"type":"selector","dimension":"isAPrivateProgram","value":true}]},{"type":"selector","dimension":"isAPrivateProgram","value":false}]}]},"aggregations":[],"postAggregations":[],"intervals":["1901-01-01T00:00:00+00:00/2101-01-01T00:00:00+00:00"]},

    "entity_assessment_query" : {"queryType":"groupBy","dataSource":"ml_assessment_data","granularity":"all","dimensions":["domainName","level","programName","criteriaDescription","childExternalid","childName","childType"],"filter":{"type":"and","fields":[{"type":"selector","dimension":"","value":""},{"type":"selector","dimension":"programId","value":""},{"type":"selector","dimension":"solutionId","value":""},{"type":"selector","dimension":"childType","value":"criteria"}]},"aggregations":[{"fieldName":"","fieldNames":[],"type":"count","name":""}],"postAggregations":[],"intervals":["1901-01-01T00:00:00+00:00/2101-01-01T00:00:00+00:00"]},

    "programs_list_query" : {"queryType":"groupBy","dataSource":"","granularity":"all","dimensions":["programId","programName"],"filter":{"type":"and","fields":[{"type":"selector","dimension":"","value":""},{"type":"or","fields":[{"type":"and","fields":[{"type":"selector","dimension":"","value":""},{"type":"selector","dimension":"isAPrivateProgram","value":true}]},{"type":"selector","dimension":"isAPrivateProgram","value":false}]}]},"aggregations":[],"postAggregations":[],"intervals":["1901-01-01T00:00:00+00:00/2101-01-01T00:00:00+00:00"]},

    "get_submissionId_count_query" : {"queryType":"groupBy","dataSource":"ml_survey","aggregations":[{"fieldName":"surveySubmissionId","fieldNames":["surveySubmissionId"],"type":"cardinality","name":"submissionIdCount"}],"granularity":"all","postAggregations":[],"intervals":"1901-01-01T00:00:00+00:00/2101-01-01T00:00:00+00:00","filter":{"type":"selector","dimension":"solutionId","value":""}},

    "survey_solutions_report_query" : {"queryType":"groupBy","dataSource":"ml_survey","granularity":"all","dimensions":["surveySubmissionId","solutionId","solutionName","questionName","questionAnswer","remarks","surveyId","questionResponseType","questionResponseLabel","questionId","questionExternalId","instanceId","instanceParentQuestion","instanceParentResponsetype","instanceParentId","instanceParentExternalId","instanceParentEcmSequence","completedDate"],"filter":{"type":"and","fields":[{"type":"selector","dimension":"solutionId","value":""},{"type":"selector","dimension":"questionResponseType","value":""},{"type":"not","field": {"type":"selector","dimension":"questionAnswer","value":""}}]},"aggregations":[],"postAggregations":[],"intervals":["1901-01-01T00:00:00+00:00/2101-01-01T00:00:0+00:00"]},

    "survey_solution_chart_report_query" : {"queryType":"groupBy","dataSource":"ml_survey","dimensions":["questionExternalId","questionName","questionResponseLabel","questionAnswer","solutionName","questionResponseType","instanceParentResponsetype","instanceParentQuestion","instanceParentId","instanceParentExternalId","instanceId"],"aggregations":[{"type":"count","name":"questionAnswerCount","fieldName":"questionAnswer"}],"granularity":"all","postAggregations":[],"intervals":"1901-01-01T00:00:00+00:00/2101-01-01T00:00:00+00:00","filter":{"type":"and","fields":[{"type":"or","fields":[{"type":"selector","dimension":"questionResponseType","value":"radio"},{"type":"selector","dimension":"questionResponseType","value":"multiselect"}]},{"type":"selector","dimension":"solutionId","value":""}]}},

    "get_survey_evidence_query" : {"queryType":"groupBy","dataSource":"ml_survey_evidence_dev","granularity":"all","dimensions":["fileSourcePath","questionExternalId","surveySubmissionId","surveyId","evidence_count","total_evidences","fileName","solutionId"],"filter":{"type":"and","fields":[{"type":"selector","dimension":"","value": ""}]},"aggregations":[],"postAggregations":[],"intervals":["1901-01-01T00:00:00+00:00/2101-01-01T00:00:00+00:00"]},

    "survey_submission_report_query" : {"queryType":"groupBy","dataSource":"ml_survey","granularity":"all","dimensions":["surveySubmissionId","solutionId","solutionName","questionName","questionAnswer","remarks","surveyId","questionResponseType","questionResponseLabel","questionId","questionExternalId","instanceId","instanceParentQuestion","instanceParentResponsetype","instanceParentId","questionSequenceByEcm","instanceParentExternalId","instanceParentEcmSequence","completedDate"],"filter":{"type":"and","fields":[{"type":"selector","dimension":"surveySubmissionId","value":""}]},"aggregations":[],"postAggregations":[],"intervals":["1901-01-01T00:00:00+00:00/2101-01-01T00:00:00+00:00"]},

    "list_all_responses" : {"queryType":"scan","dataSource":"mlv_ml_surveys","resultFormat":"list","filter":{"type":"and","fields":[{"type":"selector","dimension":"solutionId","value":""},{"type":"selector","dimension":"questionExternalId","value":""}]},"columns":["questionName","questionAnswer","surveySubmissionId","completedDate"],"intervals":["1901-01-01/2101-01-01"]},

    "content_viewed_in_platform_query" : {"queryType":"topN","dataSource":"ml_telemetry","aggregations":[{"fieldName":"content_identifier","fieldNames":["content_identifier"],"type":"count","name":"COUNT(content_identifier)"}],"granularity":"all","postAggregations":[],"intervals":"1901-01-01T00:00:00+00:00/2101-01-01T00:00:00+00:00","filter":{"type":"and","fields":[{"type":"or","fields":[{"type":"selector","dimension":"Event_type","value":"play"},{"type":"selector","dimension":"Event_type","value":"view"}]},{"type":"not","field":{"type":"selector","dimension":"content_identifier","value":null}}]},"threshold":10,"metric":"COUNT(content_identifier)","dimension":"content_name"},

    "content_downloaded_by_user_query" : {"queryType":"topN","dataSource":"ml_telemetry","aggregations":[{"fieldName":"content_identifier","fieldNames":["content_identifier"],"type":"count","name":"COUNT(content_identifier)"}],"granularity":"all","postAggregations":[],"intervals":"1901-01-01T00:00:00+00:00/2101-01-01T00:00:00+00:00","filter":{"type":"and","fields":[{"type":"selector","dimension":"User_id","value":"2b73b6d0-3b1f-4235-917f-5ee03df9450f"},{"type":"and","fields":[{"type":"selector","dimension":"Event_subtype","value":"ContentDownload-Success"},{"type":"not","field":{"type":"selector","dimension":"content_identifier","value":null}}]}]},"threshold":5,"metric":"COUNT(content_identifier)","dimension":"content_name"},

    "usage_by_content_query" : {"queryType":"topN","dataSource":"ml_telemetry","aggregations":[{"fieldName":"UserId","fieldNames":["UserId"],"type":"count","name":"Total Users Viewed"}],"granularity":"all","postAggregations":[],"intervals":"1901-01-01T00:00:00+00:00/2101-01-01T00:00:00+00:00","filter":{"type":"not","field":{"type":"selector","dimension":"content_name","value":null}},"threshold":5,"metric":"Total Users Viewed","dimension":"content_name"},

    "course_enrollment_query" : {"queryType":"groupBy","dataSource":"ml_enrollment","aggregations":[{"fieldName":"User_id","fieldNames":["User_id"],"type":"count","name":"COUNT(User_id)"}],"granularity":"all","postAggregations":[],"intervals":"1901-01-01T00:00:00+00:00/2101-01-01T00:00:00+00:00","filter":{"type":"selector","dimension":"User_id","value":""},"threshold":10000,"metric":"COUNT(User_id)","dimensions":["course_name","course_status"]},

    "list_my_solutions_query" : {"queryType":"groupBy","dataSource":"ml_observation","granularity":"all","dimensions":["solutionId","solutionName","totalScore"],"filter":{"type":"and","fields":[{"type":"selector","dimension":"","value":""},{"type":"selector","dimension":"createdBy","value":""}]},"aggregations":[],"postAggregations":[],"intervals":["1901-01-01T00:00:00+00:00/2101-01-01T00:00:00+00:00"]},

    "entity_solution_score_query" : {"queryType":"groupBy","dataSource":"ml_observation_qa","dimensions":["questionName","questionExternalId","questionResponseType","minScore","maxScore","observationSubmissionId","school","schoolName","questionId","completedDate","observationName","solutionId","solutionName"],"aggregations":[{"type":"count","name":"count"}],"granularity":"all","postAggregations":[],"intervals":"1901-01-01T00:00:00+00:00/2101-01-01T00:00:00+00:00","filter":{"type":"and","fields":[{"type":"or","fields":[{"type":"selector","dimension":"questionResponseType","value":"radio"},{"type":"selector","dimension":"questionResponseType","value":"multiselect"},{"type":"selector","dimension":"questionResponseType","value":"slider"}]},{"type":"and","fields":[{"type":"selector","dimension":"","value":"" },{"type":"selector","dimension":"solutionId","value":""}]}]},"limitSpec":{"type":"default","limit":10000,"columns":[{"dimension":"count","direction":"descending"}]}},

    "observations_by_entity" : {"queryType":"groupBy","dataSource":"ml_observation_dev","granularity":"all","dimensions":["entityId","entityName","observationName","observationSubmissionId","createdAt"],"filter":{"type":"or","fields":[]},"aggregations":[],"postAggregations":[],"intervals":["1901-01-01T00:00:00+00:00/2101-01-01T00:00:00+00:00"]},
    
    "question_response_query" : {"queryType":"scan","dataSource":"sl-observation","resultFormat": "list","columns":[ "solutionName", "criteriaName", "domainName", "questionName", "programName", "questionResponseLabel", "observationSubmissionId", "questionResponseType", "questionId", "questionSequenceByEcm","solution_type"],"filter": {"type":"and","fields": [ { "type": "or", "fields": [ { "type": "selector", "dimension": "questionResponseType", "value": "radio" }, { "type": "selector", "dimension": "questionResponseType", "value": "multiselect" }, { "type": "selector", "dimension": "questionResponseType", "value": "slider" } ] } ] },"intervals":"1901-01-01T00:00:00+00:00/2101-01-01T00:00:00+00:00"}
}